NOWNT/Database.py
NOWNT/Task.py
NOWNT/Test.py
NOWNT/User.py
NOWNT/__init__.py
NOWNT/web.py
NOWNT/static/styles/styles.css
NOWNT/templates/base.html
NOWNT/templates/index.html
NOWNT/templates/previous.html
NOWNT/templates/results.html
freelancing_project_2021-1.dist-info/LICENSE
freelancing_project_2021-1.dist-info/METADATA
freelancing_project_2021-1.dist-info/WHEEL
freelancing_project_2021-1.dist-info/top_level.txt
freelancing_project_2021-1.dist-info/RECORD
