Metadata-Version: 2.1
Name: freelancing-project-2021
Version: 1
Summary: UNKNOWN
Home-page: UNKNOWN
Author: Abdallah Ziad
Author-email: boodyziad1@gmail.com
License: UNKNOWN
Platform: UNKNOWN
Classifier: Programming Language :: Python :: 3
Classifier: Operating System :: OS Independent
Requires-Python: >=3.6
License-File: LICENSE
